# 关于Java4种自增方法的不同

## 4种自增的方法
- i++
- ++i
- i+=1
- i=i+1

## 示例代码

```java
public class HelloWorld{
	
	public static void main(String[] args){
		method1();// i=i+1
		method2();// i+=1
		method3();// i++
		method4();// ++i
	}
	
	public static void method1(){
		int i = 0;
		System.out.println(i = i + 1);
	}
	
	public static void method2(){
		int i = 0;
		System.out.println(i += 1);
	}
	
	public static void method3(){
		int i = 0;
		System.out.println(i++);
	}
	
	public static void method4(){
		int i = 0;
		System.out.println(++i);
	}
}
```
## 运行结果

```java
1
1
0
1
```
## 解释说明
+ 第一种```i=i+1```:首先```=```的优先级小于```+```，所以该表达式会首先进行加法操作，然后再进行赋值操作
+ 第二种```i+=1```:与```i++```相同;
+ 第三种```i++```:先参与操作，后自增
+ 第四种```++i```:先自增，后参与操作
以上都是大家都熟知的想法
## 从字节码的角度


Compiled from "HelloWorld.java"
public class HelloWorld {
  public HelloWorld();
    Code:
       0: aload_0
       1: invokespecial #1                  // Method java/lang/Object."<init>":()V
       4: return

  public static void main(java.lang.String[]);
    Code:
       0: invokestatic  #2                  // Method method1:()V
       3: invokestatic  #3                  // Method method2:()V
       6: invokestatic  #4                  // Method method3:()V
       9: invokestatic  #5                  // Method method4:()V
      12: return

  public static void method1();
    Code:
       0: iconst_0
       1: istore_0
       2: iload_0
       3: iconst_1
       4: iadd
       5: istore_0
       6: getstatic     #6                  // Field java/lang/System.out:Ljava/io/PrintStream;
       9: iload_0
      10: invokevirtual #7                  // Method java/io/PrintStream.println:(I)V
      13: return

  public static void method2();
    Code:
       0: iconst_0
       1: istore_0
       2: iinc          0, 1
       5: getstatic     #6                  // Field java/lang/System.out:Ljava/io/PrintStream;
       8: iload_0
       9: invokevirtual #7                  // Method java/io/PrintStream.println:(I)V
      12: return

  public static void method3();
    Code:
       0: iconst_0
       1: istore_0
       2: getstatic     #6                  // Field java/lang/System.out:Ljava/io/PrintStream;
       5: iload_0
       6: iinc          0, 1
       9: invokevirtual #7                  // Method java/io/PrintStream.println:(I)V
      12: return

  public static void method4();
    Code:
       0: iconst_0
       1: istore_0
       2: getstatic     #6                  // Field java/lang/System.out:Ljava/io/PrintStream;
       5: iinc          0, 1
       8: iload_0
       9: invokevirtual #7                  // Method java/io/PrintStream.println:(I)V
      12: return
}
```
